LICENSE
MANIFEST.in
README.rst
requirements.txt
setup.py
paperpal/__init__.py
paperpal/__main__.py
paperpal/fix_bibliography.py
paperpal/k2pdfopt_wrapper.py
paperpal/modification_time.py
paperpal/resource_path.py
paperpal/zotero-bridge.js
paperpal/zotero.py
paperpal.egg-info/PKG-INFO
paperpal.egg-info/SOURCES.txt
paperpal.egg-info/dependency_links.txt
paperpal.egg-info/entry_points.txt
paperpal.egg-info/requires.txt
paperpal.egg-info/top_level.txt