Metadata-Version: 1.1
Name: paperpal
Version: 0.3.0
Summary: Paper management with Zotero
Home-page: http://github.com/eddieantonio/paperpal
Author: Eddie Antonio Santos
Author-email: easantos@ualberta.ca
License: Apache 2.0
Platform: UNKNOWN
Classifier: Development Status :: 4 - Beta
Classifier: License :: OSI Approved :: Apache Software License
Classifier: Programming Language :: Python :: 2.7
Classifier: Topic :: Text Processing :: Indexing
